ttf_opensans/__init__.py
ttf_opensans/ttf/OpenSans-Bold.ttf
ttf_opensans/ttf/OpenSans-BoldItalic.ttf
ttf_opensans/ttf/OpenSans-ExtraBold.ttf
ttf_opensans/ttf/OpenSans-ExtraBoldItalic.ttf
ttf_opensans/ttf/OpenSans-Italic.ttf
ttf_opensans/ttf/OpenSans-Light.ttf
ttf_opensans/ttf/OpenSans-LightItalic.ttf
ttf_opensans/ttf/OpenSans-Regular.ttf
ttf_opensans/ttf/OpenSans-SemiBold.ttf
ttf_opensans/ttf/OpenSans-SemiBoldItalic.ttf
ttf_opensans-2020.10.30.dist-info/LICENSE
ttf_opensans-2020.10.30.dist-info/METADATA
ttf_opensans-2020.10.30.dist-info/WHEEL
ttf_opensans-2020.10.30.dist-info/top_level.txt
ttf_opensans-2020.10.30.dist-info/RECORD
