Metadata-Version: 2.1
Name: ttf-opensans
Version: 2020.10.30
Summary: ttf-opensans is a Python package vending the Open Sans font by Steve Matteson.
Home-page: https://github.com/Gorialis/ttf-opensans
Author: Devon (Gorialis) R
License: Apache 2.0
Download-URL: https://github.com/Gorialis/ttf-opensans/archive/v2020.10.30.tar.gz
Project-URL: Code, https://github.com/Gorialis/ttf-opensans
Project-URL: Issue tracker, https://github.com/Gorialis/ttf-opensans/issues
Keywords: font fonts ttf
Platform: UNKNOWN
Classifier: Development Status :: 5 - Production/Stable
Classifier: Intended Audience :: Developers
Classifier: License :: OSI Approved :: Apache Software License
Classifier: Operating System :: OS Independent
Classifier: Programming Language :: Python :: 3 :: Only
Classifier: Programming Language :: Python :: 3.4
Classifier: Programming Language :: Python :: 3.5
Classifier: Programming Language :: Python :: 3.6
Classifier: Programming Language :: Python :: 3.7
Classifier: Programming Language :: Python :: 3.8
Classifier: Programming Language :: Python :: 3.9
Classifier: Topic :: Multimedia :: Graphics
Classifier: Topic :: Text Processing :: Fonts
Requires-Python: >=3.4.0
